README.md
setup.py
satproc.egg-info/PKG-INFO
satproc.egg-info/SOURCES.txt
satproc.egg-info/dependency_links.txt
satproc.egg-info/top_level.txt
src/__init__.py
src/data/__init__.py
src/data/make_dataset.py
src/features/__init__.py
src/features/build_features.py
src/models/__init__.py
src/models/predict_model.py
src/models/train_model.py
src/visualization/__init__.py
src/visualization/visualize.py