Metadata-Version: 1.0
Name: satproc
Version: 0.1.0
Summary: Python package for satellite data download and processing.
Home-page: UNKNOWN
Author: Jacob Høxbroe Jeppesen
Author-email: UNKNOWN
License: MIT
Platform: UNKNOWN
